awesome_caching/__init__.py
awesome_caching/cache.py
awesome_caching/backends/__init__.py
awesome_caching/backends/base_cache.py
awesome_caching/backends/null_cache.py
awesome_caching/backends/redis_cache.py
awesome_caching/backends/simple_cache.py
awesome_caching-0.0.2.dist-info/LICENSE.md
awesome_caching-0.0.2.dist-info/METADATA
awesome_caching-0.0.2.dist-info/WHEEL
awesome_caching-0.0.2.dist-info/top_level.txt
awesome_caching-0.0.2.dist-info/zip-safe
awesome_caching-0.0.2.dist-info/RECORD
